{"nodes":[{"username":"Pubski","num_posts":1},{"username":"thenewgreen","num_posts":1},{"username":"lil","num_posts":3},{"username":"kleinbl00","num_posts":4},{"username":"ThatFanficGuy","num_posts":6},{"username":"steve","num_posts":7},{"username":"ButterflyEffect","num_posts":2},{"username":"cgod","num_posts":2},{"username":"flac","num_posts":3},{"username":"WanderingEng","num_posts":2},{"username":"veen","num_posts":1},{"username":"mk","num_posts":3},{"username":"rjw","num_posts":1},{"username":"johnnyFive","num_posts":3},{"username":"flagamuffin","num_posts":1},{"username":"Creativity","num_posts":1},{"username":"blackbootz","num_posts":1},{"username":"snoodog","num_posts":1},{"username":"goobster","num_posts":1},{"username":"StJohn","num_posts":1},{"username":"rezzeJ","num_posts":2},{"username":"johan","num_posts":2},{"username":"zebra2","num_posts":1},{"username":"Trombone","num_posts":1},{"username":"","num_posts":3},{"username":"OftenBen","num_posts":1},{"username":"AnSionnachRua","num_posts":1},{"username":"elizabeth","num_posts":2},{"username":"b_b","num_posts":1},{"username":"c_hawkthorne","num_posts":1},{"username":"ThurberMingus","num_posts":1}],"edges":[{"source":"thenewgreen","target":"Pubski"},{"source":"lil","target":"thenewgreen"},{"source":"kleinbl00","target":"lil"},{"source":"ThatFanficGuy","target":"thenewgreen"},{"source":"steve","target":"thenewgreen"},{"source":"ButterflyEffect","target":"Pubski"},{"source":"cgod","target":"Pubski"},{"source":"flac","target":"cgod"},{"source":"WanderingEng","target":"Pubski"},{"source":"ButterflyEffect","target":"WanderingEng"},{"source":"WanderingEng","target":"ButterflyEffect"},{"source":"veen","target":"Pubski"},{"source":"mk","target":"veen"},{"source":"kleinbl00","target":"mk"},{"source":"rjw","target":"mk"},{"source":"ThatFanficGuy","target":"mk"},{"source":"johnnyFive","target":"ThatFanficGuy"},{"source":"flagamuffin","target":"veen"},{"source":"Creativity","target":"veen"},{"source":"steve","target":"Pubski"},{"source":"blackbootz","target":"steve"},{"source":"steve","target":"blackbootz"},{"source":"snoodog","target":"steve"},{"source":"steve","target":"snoodog"},{"source":"lil","target":"steve"},{"source":"steve","target":"lil"},{"source":"ThatFanficGuy","target":"steve"},{"source":"steve","target":"ThatFanficGuy"},{"source":"ThatFanficGuy","target":"steve"},{"source":"johnnyFive","target":"steve"},{"source":"goobster","target":"steve"},{"source":"kleinbl00","target":"steve"},{"source":"steve","target":"kleinbl00"},{"source":"flac","target":"Pubski"},{"source":"cgod","target":"flac"},{"source":"flac","target":"cgod"},{"source":"mk","target":"Pubski"},{"source":"StJohn","target":"mk"},{"source":"lil","target":"StJohn"},{"source":"rezzeJ","target":"mk"},{"source":"mk","target":"rezzeJ"},{"source":"rezzeJ","target":"mk"},{"source":"johan","target":"Pubski"},{"source":"zebra2","target":"johan"},{"source":"johan","target":"zebra2"},{"source":"Trombone","target":"Pubski"},{"source":"kleinbl00","target":"Pubski"},{"source":"","target":"Pubski"},{"source":"OftenBen","target":""},{"source":"","target":"OftenBen"},{"source":"AnSionnachRua","target":"Pubski"},{"source":"ThatFanficGuy","target":"AnSionnachRua"},{"source":"elizabeth","target":"ThatFanficGuy"},{"source":"ThatFanficGuy","target":"elizabeth"},{"source":"elizabeth","target":"ThatFanficGuy"},{"source":"johnnyFive","target":"Pubski"},{"source":"b_b","target":"Pubski"},{"source":"c_hawkthorne","target":"Pubski"},{"source":"ThurberMingus","target":"Pubski"},{"source":"","target":"Pubski"}],"meta":{"title":"Pubski: May 10, 2017","post_date":" May 10, 2017","post_link":"http://hubski.com/pub/381209","comment_count":"59","top_commenter":"thenewgreen","hubwheel_dots":"8","num_badges":0}}