{"nodes":[{"username":"Pubski","num_posts":1},{"username":"Devac","num_posts":1},{"username":"kantos","num_posts":1},{"username":"galen","num_posts":4},{"username":"kleinbl00","num_posts":7},{"username":"zebra2","num_posts":4},{"username":"nil","num_posts":2},{"username":"Foveaux","num_posts":4},{"username":"swedishbadgergirl","num_posts":1},{"username":"elizabeth","num_posts":4},{"username":"veen","num_posts":1},{"username":"Creativity","num_posts":1},{"username":"","num_posts":4},{"username":"kingmudsy","num_posts":3},{"username":"goobster","num_posts":5},{"username":"OftenBen","num_posts":1},{"username":"mk","num_posts":1}],"edges":[{"source":"Devac","target":"Pubski"},{"source":"kantos","target":"Devac"},{"source":"galen","target":"Pubski"},{"source":"galen","target":"galen"},{"source":"kleinbl00","target":"galen"},{"source":"galen","target":"kleinbl00"},{"source":"zebra2","target":"galen"},{"source":"nil","target":"galen"},{"source":"kleinbl00","target":"Pubski"},{"source":"Foveaux","target":"kleinbl00"},{"source":"kleinbl00","target":"Foveaux"},{"source":"galen","target":"kleinbl00"},{"source":"kleinbl00","target":"galen"},{"source":"swedishbadgergirl","target":"Pubski"},{"source":"elizabeth","target":"Pubski"},{"source":"nil","target":"elizabeth"},{"source":"elizabeth","target":"nil"},{"source":"veen","target":"elizabeth"},{"source":"elizabeth","target":"veen"},{"source":"Creativity","target":"elizabeth"},{"source":"","target":"Pubski"},{"source":"kingmudsy","target":""},{"source":"","target":"kingmudsy"},{"source":"zebra2","target":""},{"source":"","target":"zebra2"},{"source":"kingmudsy","target":""},{"source":"","target":"kingmudsy"},{"source":"kingmudsy","target":""},{"source":"Foveaux","target":"Pubski"},{"source":"goobster","target":"Foveaux"},{"source":"Foveaux","target":"goobster"},{"source":"OftenBen","target":"Foveaux"},{"source":"Foveaux","target":"OftenBen"},{"source":"goobster","target":"Pubski"},{"source":"kleinbl00","target":"goobster"},{"source":"elizabeth","target":"kleinbl00"},{"source":"kleinbl00","target":"elizabeth"},{"source":"goobster","target":"kleinbl00"},{"source":"kleinbl00","target":"goobster"},{"source":"mk","target":"Pubski"},{"source":"zebra2","target":"Pubski"},{"source":"goobster","target":"zebra2"},{"source":"zebra2","target":"goobster"},{"source":"goobster","target":"zebra2"}],"meta":{"title":"Pubski: September 25, 2019","post_date":" September 25, 2019","post_link":"http://hubski.com/pub/429009","comment_count":"44","top_commenter":"Devac","hubwheel_dots":"8","num_badges":0}}