{"nodes":[{"username":"Pubski","num_posts":1},{"username":"kleinbl00","num_posts":6},{"username":"moslydeaf","num_posts":4},{"username":"_refugee_","num_posts":3},{"username":"lil","num_posts":1},{"username":"Devac","num_posts":3},{"username":"goobster","num_posts":7},{"username":"veen","num_posts":2},{"username":"WanderingEng","num_posts":4},{"username":"cgod","num_posts":1},{"username":"zebra2","num_posts":2},{"username":"OftenBen","num_posts":2},{"username":"legend","num_posts":1},{"username":"darlinareyousleepy","num_posts":1},{"username":"Quatrarius","num_posts":1}],"edges":[{"source":"kleinbl00","target":"Pubski"},{"source":"moslydeaf","target":"kleinbl00"},{"source":"kleinbl00","target":"moslydeaf"},{"source":"moslydeaf","target":"kleinbl00"},{"source":"kleinbl00","target":"moslydeaf"},{"source":"_refugee_","target":"Pubski"},{"source":"_refugee_","target":"_refugee_"},{"source":"lil","target":"_refugee_"},{"source":"_refugee_","target":"lil"},{"source":"Devac","target":"Pubski"},{"source":"goobster","target":"Devac"},{"source":"Devac","target":"goobster"},{"source":"goobster","target":"Devac"},{"source":"kleinbl00","target":"Devac"},{"source":"Devac","target":"kleinbl00"},{"source":"kleinbl00","target":"Devac"},{"source":"veen","target":"Pubski"},{"source":"WanderingEng","target":"veen"},{"source":"veen","target":"WanderingEng"},{"source":"goobster","target":"Pubski"},{"source":"cgod","target":"goobster"},{"source":"moslydeaf","target":"Pubski"},{"source":"goobster","target":"moslydeaf"},{"source":"moslydeaf","target":"goobster"},{"source":"goobster","target":"moslydeaf"},{"source":"zebra2","target":"Pubski"},{"source":"WanderingEng","target":"Pubski"},{"source":"goobster","target":"WanderingEng"},{"source":"WanderingEng","target":"goobster"},{"source":"goobster","target":"WanderingEng"},{"source":"OftenBen","target":"goobster"},{"source":"WanderingEng","target":"goobster"},{"source":"legend","target":"Pubski"},{"source":"zebra2","target":"legend"},{"source":"darlinareyousleepy","target":"Pubski"},{"source":"OftenBen","target":"Pubski"},{"source":"Quatrarius","target":"Pubski"},{"source":"kleinbl00","target":"Quatrarius"}],"meta":{"title":"Pubski: December 5, 2018","post_date":" December 5, 2018","post_link":"http://hubski.com/pub/419190","comment_count":"37","top_commenter":"kleinbl00","hubwheel_dots":"8","num_badges":0}}